README.md
setup.cfg
setup.py
distributions_sp97/Binomialdistribution.py
distributions_sp97/Gaussiandistribution.py
distributions_sp97/Generaldistribution.py
distributions_sp97/__init__.py
distributions_sp97.egg-info/PKG-INFO
distributions_sp97.egg-info/SOURCES.txt
distributions_sp97.egg-info/dependency_links.txt
distributions_sp97.egg-info/not-zip-safe
distributions_sp97.egg-info/top_level.txt